datasette_updated/__init__.py
datasette_updated/templates/_footer.html
datasette_updated-0.2.0.dist-info/LICENSE
datasette_updated-0.2.0.dist-info/METADATA
datasette_updated-0.2.0.dist-info/WHEEL
datasette_updated-0.2.0.dist-info/entry_points.txt
datasette_updated-0.2.0.dist-info/top_level.txt
datasette_updated-0.2.0.dist-info/RECORD
