Metadata-Version: 2.1
Name: datasette-updated
Version: 0.2.0
Summary: Display the date your data was updated
Author-email: Ryan Caught <rcaught@gmail.com>
License: Apache-2.0
Project-URL: Homepage, https://github.com/rcaught/datasette-updated
Project-URL: Changelog, https://github.com/rcaught/datasette-updated/releases
Project-URL: Issues, https://github.com/rcaught/datasette-updated/issues
Project-URL: CI, https://github.com/rcaught/datasette-updated/actions
Classifier: Framework :: Datasette
Classifier: License :: OSI Approved :: Apache Software License
Requires-Python: >=3.8
License-File: LICENSE
Requires-Dist: datasette
Requires-Dist: deepmerge
Provides-Extra: test
Requires-Dist: pytest ; extra == 'test'
Requires-Dist: pytest-asyncio ; extra == 'test'
Requires-Dist: sqlite-utils ; extra == 'test'
